pdbx/__init__.py
pdbx/_version.py
pdbx/containers.py
pdbx/errors.py
pdbx/reader.py
pdbx/writer.py
mmcif_pdbx-2.0.1.dist-info/LICENSE
mmcif_pdbx-2.0.1.dist-info/METADATA
mmcif_pdbx-2.0.1.dist-info/WHEEL
mmcif_pdbx-2.0.1.dist-info/top_level.txt
mmcif_pdbx-2.0.1.dist-info/zip-safe
mmcif_pdbx-2.0.1.dist-info/RECORD
