Metadata-Version: 2.1
Name: mmcif-pdbx
Version: 2.0.1
Summary: Python utilities for PDBx/mmCIF storage model
Home-page: https://github.com/Electrostatics/mmcif_pdbx
Author: John Westbrook
Author-email: jwest@rcsb.rutgers.edu
Maintainer: Nathan Baker
Maintainer-email: nathanandrewbaker@gmail.com
License: UNKNOWN
Platform: UNKNOWN
Classifier: Development Status :: 4 - Beta
Classifier: Environment :: Console
Classifier: License :: CC0 1.0 Universal (CC0 1.0) Public Domain Dedication
Classifier: Natural Language :: English
Classifier: Operating System :: OS Independent
Classifier: Programming Language :: Python :: 3.6
Classifier: Programming Language :: Python :: 3.7
Classifier: Programming Language :: Python :: 3.8
Classifier: Programming Language :: Python :: 3.9
Classifier: Topic :: Scientific/Engineering :: Bio-Informatics
Classifier: Topic :: Scientific/Engineering :: Chemistry
Requires-Python: >=3.6
